Workbook

Sheet Corte
A2: Darca II — Corte 01
B3: Periodo: 24/08/2026 al 19/09/2026 · Valores en COP
B4: DEFINITIVO — verificar registro JSON del histórico
B5: Generado: 22/09/2026 12:45:54 (UTC-0500)
A8: Ítem | B8: Actividad | C8: Descripción | D8: Unidad | E8: Cantidad contratada | F8: Cantidad corte anterior | G8: Cantidad corte actual | H8: Cantidad ejecutada acumulada | I8: Precio unitario | J8: Valor corte actual | K8: Cantidad restante | L8: Valor restante | M8: Porcentaje ejecutado
A9: 1 | B9: ='Presupuesto'!B6 -> Limpieza superficie | C9: ='Presupuesto'!C6 -> Limpieza de fachada en ladrillo, incluyendo la eliminación de hollín, marcas color naranja y mugre por polución ambiental, utilizando hidrolavadora de 3000 psi. | D9: ='Presupuesto'!D6 -> m² | E9: ='Presupuesto'!E6 -> 3744 | F9: 0 | G9: =SUMIFS('Consolidado reportes'!$J$6:$J$30,'Consolidado reportes'!$K$6:$K$30,A9)-F9 -> 1872 | H9: =F9+G9 -> 1872 | I9: ='Presupuesto'!F6 -> 2707.0473 | J9: =G9*I9 -> 5067592.5 | K9: =E9-H9 -> 1872 | L9: =K9*I9 -> 5067592.5 | M9: =H9/E9 -> 0.5
A10: 2 | B10: ='Presupuesto'!B7 -> Reparaciones menores | C10: ='Presupuesto'!C7 -> Reemplazo de piezas rotas o deterioradas, emboquillado de fisuras con mortero impermeabilizado y Sika Latex. | D10: ='Presupuesto'!D7 -> und | E10: ='Presupuesto'!E7 -> 500 | F10: 0 | G10: =SUMIFS('Consolidado reportes'!$J$6:$J$30,'Consolidado reportes'!$K$6:$K$30,A10)-F10 -> 268 | H10: =F10+G10 -> 268 | I10: ='Presupuesto'!F7 -> 12761.794 | J10: =G10*I10 -> 3420160.9 | K10: =E10-H10 -> 232 | L10: =K10*I10 -> 2960736.3 | M10: =H10/E10 -> 0.536
A11: 3 | B11: ='Presupuesto'!B8 -> Protecciones | C11: ='Presupuesto'!C8 -> Protección de ventanas con plástico y limpieza de vidrios y marcos. | D11: ='Presupuesto'!D8 -> m² | E11: ='Presupuesto'!E8 -> 1800 | F11: 0 | G11: =SUMIFS('Consolidado reportes'!$J$6:$J$30,'Consolidado reportes'!$K$6:$K$30,A11)-F11 -> 900 | H11: =F11+G11 -> 900 | I11: ='Presupuesto'!F8 -> 4157.2511 | J11: =G11*I11 -> 3741526 | K11: =E11-H11 -> 900 | L11: =K11*I11 -> 3741526 | M11: =H11/E11 -> 0.5
A12: 4 | B12: ='Presupuesto'!B9 -> Emboquillado | C12: ='Presupuesto'!C9 -> Suministro y aplicación de mortero impermeabilizante en toda la fachada, incluyendo muros laterales. | D12: ='Presupuesto'!D9 -> m² | E12: ='Presupuesto'!E9 -> 3744 | F12: 0 | G12: =SUMIFS('Consolidado reportes'!$J$6:$J$30,'Consolidado reportes'!$K$6:$K$30,A12)-F12 -> 1872 | H12: =F12+G12 -> 1872 | I12: ='Presupuesto'!F9 -> 4060.5709 | J12: =G12*I12 -> 7601388.7 | K12: =E12-H12 -> 1872 | L12: =K12*I12 -> 7601388.7 | M12: =H12/E12 -> 0.5
A13: 5 | B13: ='Presupuesto'!B10 -> Lavado | C13: ='Presupuesto'!C10 -> Lavado con rinse o ácido especializado para fachadas, tras el emboquillado. | D13: ='Presupuesto'!D10 -> m² | E13: ='Presupuesto'!E10 -> 3744 | F13: 0 | G13: =SUMIFS('Consolidado reportes'!$J$6:$J$30,'Consolidado reportes'!$K$6:$K$30,A13)-F13 -> 1872 | H13: =F13+G13 -> 1872 | I13: ='Presupuesto'!F10 -> 6090.8563 | J13: =G13*I13 -> 11402083 | K13: =E13-H13 -> 1872 | L13: =K13*I13 -> 11402083 | M13: =H13/E13 -> 0.5
A14: 6 | B14: ='Presupuesto'!B11 -> Suministro y aplicación | C14: ='Presupuesto'!C11 -> Aplicación de dos manos de SIKA impermeabilizante 10 años, en toda la fachada, incluyendo muros laterales y ladrillo del cerramiento, con aspersor a 360 psi. | D14: ='Presupuesto'!D11 -> m² | E14: ='Presupuesto'!E11 -> 3744 | F14: 0 | G14: =SUMIFS('Consolidado reportes'!$J$6:$J$30,'Consolidado reportes'!$K$6:$K$30,A14)-F14 -> 1872 | H14: =F14+G14 -> 1872 | I14: ='Presupuesto'!F11 -> 11359.93 | J14: =G14*I14 -> 21265790 | K14: =E14-H14 -> 1872 | L14: =K14*I14 -> 21265790 | M14: =H14/E14 -> 0.5
A15: 7 | B15: ='Presupuesto'!B12 -> Resane y reparación | C15: ='Presupuesto'!C12 -> Resane de muros laterales, impermeabilización y pintura color blanca de alta resistencia. | D15: ='Presupuesto'!D12 -> m² | E15: ='Presupuesto'!E12 -> 270 | F15: 0 | G15: =SUMIFS('Consolidado reportes'!$J$6:$J$30,'Consolidado reportes'!$K$6:$K$30,A15)-F15 -> 0 | H15: =F15+G15 -> 0 | I15: ='Presupuesto'!F12 -> 18272.569 | J15: =G15*I15 -> 0 | K15: =E15-H15 -> 270 | L15: =K15*I15 -> 4933593.6 | M15: =H15/E15 -> 0
A16: 8 | B16: ='Presupuesto'!B13 -> Vidrios y marcos | C16: ='Presupuesto'!C13 -> Lavado de vidrios, incluyendo flanches | D16: ='Presupuesto'!D13 -> m² | E16: ='Presupuesto'!E13 -> 1800 | F16: 0 | G16: =SUMIFS('Consolidado reportes'!$J$6:$J$30,'Consolidado reportes'!$K$6:$K$30,A16)-F16 -> 0 | H16: =F16+G16 -> 0 | I16: ='Presupuesto'!F13 -> 6284.2169 | J16: =G16*I16 -> 0 | K16: =E16-H16 -> 1800 | L16: =K16*I16 -> 11311590 | M16: =H16/E16 -> 0
A17: 9 | B17: ='Presupuesto'!B14 -> Vidrios y marcos | C17: ='Presupuesto'!C14 -> Pintura de marcos y flanches, aplicación de silicona antihongos y reparación de marcos defectuosos. | D17: ='Presupuesto'!D14 -> ml | E17: ='Presupuesto'!E14 -> 1248 | F17: 0 | G17: =SUMIFS('Consolidado reportes'!$J$6:$J$30,'Consolidado reportes'!$K$6:$K$30,A17)-F17 -> 0 | H17: =F17+G17 -> 0 | I17: ='Presupuesto'!F14 -> 10344.788 | J17: =G17*I17 -> 0 | K17: =E17-H17 -> 1248 | L17: =K17*I17 -> 12910295 | M17: =H17/E17 -> 0
A18: 10 | B18: ='Presupuesto'!B15 -> Fachada flotante | C18: ='Presupuesto'!C15 -> Lavado de vidrios, incluyendo la marquesina. | D18: ='Presupuesto'!D15 -> m² | E18: ='Presupuesto'!E15 -> 640 | F18: 0 | G18: =SUMIFS('Consolidado reportes'!$J$6:$J$30,'Consolidado reportes'!$K$6:$K$30,A18)-F18 -> 0 | H18: =F18+G18 -> 0 | I18: ='Presupuesto'!F15 -> 6284.2169 | J18: =G18*I18 -> 0 | K18: =E18-H18 -> 640 | L18: =K18*I18 -> 4021898.8 | M18: =H18/E18 -> 0
A19: 11 | B19: ='Presupuesto'!B16 -> Concreto abuzar | C19: ='Presupuesto'!C16 -> Lavado de concreto en fachada flotante, tanto interno como externo. | D19: ='Presupuesto'!D16 -> m² | E19: ='Presupuesto'!E16 -> 192 | F19: 0 | G19: =SUMIFS('Consolidado reportes'!$J$6:$J$30,'Consolidado reportes'!$K$6:$K$30,A19)-F19 -> 0 | H19: =F19+G19 -> 0 | I19: ='Presupuesto'!F16 -> 6960.9787 | J19: =G19*I19 -> 0 | K19: =E19-H19 -> 192 | L19: =K19*I19 -> 1336507.9 | M19: =H19/E19 -> 0
A20: 12 | B20: ='Presupuesto'!B17 -> Ductos de gas | C20: ='Presupuesto'!C17 -> Lijado y limpieza de ductos de gas en áreas de cocina | D20: ='Presupuesto'!D17 -> m² | E20: ='Presupuesto'!E17 -> 180 | F20: 0 | G20: =SUMIFS('Consolidado reportes'!$J$6:$J$30,'Consolidado reportes'!$K$6:$K$30,A20)-F20 -> 0 | H20: =F20+G20 -> 0 | I20: ='Presupuesto'!F17 -> 6477.5774 | J20: =G20*I20 -> 0 | K20: =E20-H20 -> 180 | L20: =K20*I20 -> 1165963.9 | M20: =H20/E20 -> 0
... A22: 14 | B22: ='Presupuesto'!B19 -> Rejillas | C22: ='Presupuesto'!C19 -> Limpieza de rejillas de contadores | D22: ='Presupuesto'!D19 -> m² | E22: ='Presupuesto'!E19 -> 40 | F22: 0 | G22: =SUMIFS('Consolidado reportes'!$J$6:$J$30,'Consolidado reportes'!$K$6:$K$30,A22)-F22 -> 0 | H22: =F22+G22 -> 0 | I22: ='Presupuesto'!F19 -> 9668.0259 | J22: =G22*I22 -> 0 | K22: =E22-H22 -> 40 | L22: =K22*I22 -> 386721.04 | M22: =H22/E22 -> 0
L25: Porcentaje | M25: Base
B26: Costos directos ejecutados | I26: =SUM(J9:J22) -> 52498541
B27: Administración | I27: =I26*L27 -> 5249854.1 | L27: ='Presupuesto'!E23 -> 0.1
B28: Imprevistos | I28: =I26*L28 -> 2099941.6 | L28: ='Presupuesto'!E24 -> 0.04
B29: Utilidad | I29: =I26*L29 -> 2624927 | L29: ='Presupuesto'!E25 -> 0.05
B30: IVA sobre utilidad | I30: =I29*L30 -> 498736.14 | L30: ='Presupuesto'!E26 -> 0.19
B31: Valor bruto del corte | I31: =SUM(I26:I30) -> 62972000
B32: Amortización del anticipo | I32: =IF(M32="bruto",I31,IF(M32="directos",I26,IF(M32="utilidad",I29,NA())))*L32 -> 6297200 | L32: 0.1 | M32: bruto
B33: Retención en la fuente | I33: =(I31-I30)*L33 -> 1249465.3 | L33: 0.02 | M33: Bruto menos IVA
B34: Retención de garantía | I34: =IF(M34="bruto",I31,IF(M34="directos",I26,IF(M34="utilidad",I29,NA())))*L34 -> 6297200 | L34: 0.1 | M34: bruto
B35: Otros descuentos | I35: 0
B36: Valor neto a pagar | I36: =I31-SUM(I32:I35) -> 49128135
B38: Valor total contratado | I38: ='Presupuesto'!G29 -> 170000000
B39: Valor ejecutado acumulado (AIU e IVA) | I39: =SUMPRODUCT(H9:H22,I9:I22)*(1+L27+L28+L29*(1+L30)) -> 62972000
B40: Valor pendiente por ejecutar (AIU e IVA) | I40: =I38-I39 -> 1.07028e+08
B43: Fecha inicial | I43: 46258
B44: Fecha final | I44: 46284
B45: Número de corte | I45: 1
B46: Fecha y hora de generación | I46: 46287.532

Sheet Consolidado reportes
A2: Consolidado por WBS
A3: Fuente: DATOS. Las columnas semanales son cantidades ejecutadas; se incluyen semanas anteriores para calcular el acumulado.
A5: WBS | B5: Actividad | C5: Tramo | D5: Unidad | E5: Cantidad total del tramo | F5: Avance_Real_DARCA2_ 24Ago-29Ago.xlsx | G5: Avance_Real_DARCA2_ 31Ago-05Sep.xlsx | H5: Avance_Real_DARCA2_ 7Sep-12Sep.xlsx | I5: Avance_Real_DARCA2_ 14Sep-19Sep.xlsx | J5: Cantidad acumulada | K5: Ítem contractual
A6: 1.1.1 | B6: Protección de ventanas con plástico | C6: TRAMO 1 | D6: m² | E6: 900 | F6: 900 | G6: 0 | H6: 0 | I6: 0 | J6: =SUM(F6:I6) -> 900 | K6: 3
A7: 1.1.2 | B7: Limpieza de fachada en ladrillo - Prelavado | C7: TRAMO 1 | D7: m² | E7: 1872 | F7: 936 | G7: 936 | H7: 0 | I7: 0 | J7: =SUM(F7:I7) -> 1872 | K7: 1
A8: 1.1.3 | B8: Reemplazo de piezas rotas o deterioradas | C8: TRAMO 1 | D8: und | E8: 268 | F8: 0 | G8: 0 | H8: 238 | I8: 30 | J8: =SUM(F8:I8) -> 268 | K8: 2
A9: 1.1.4 | B9: Suministro y aplicación de mortero | C9: TRAMO 1 | D9: m² | E9: 1872 | F9: 0 | G9: 1872 | H9: 0 | I9: 0 | J9: =SUM(F9:I9) -> 1872 | K9: 4
A10: 1.1.5 | B10: Lavado con rinse o ácido especializado | C10: TRAMO 1 | D10: m² | E10: 1872 | F10: 0 | G10: 0 | H10: 1310.4 | I10: 561.6 | J10: =SUM(F10:I10) -> 1872 | K10: 5
A11: 1.1.6 | B11: Aplicación SIKA impermeabilizante 10 años | C11: TRAMO 1 | D11: m² | E11: 1872 | F11: 0 | G11: 0 | H11: 0 | I11: 1872 | J11: =SUM(F11:I11) -> 1872 | K11: 6
A12: 1.1.7 | B12: Pintura de marcos y flanches, aplicación de silicona antihongos | C12: TRAMO 1 | D12: ml | E12: 624 | F12: 0 | G12: 0 | H12: 0 | I12: 0 | J12: =SUM(F12:I12) -> 0 | K12: 9
A13: 1.1.8 | B13: Lavado de vidrios, incluyendo flanches | C13: TRAMO 1 | D13: m² | E13: 900 | F13: 0 | G13: 0 | H13: 0 | I13: 0 | J13: =SUM(F13:I13) -> 0 | K13: 8
A14: 1.1.9 | B14: Limpieza de tuberías de cobre | C14: TRAMO 1 | D14: ml | E14: 100 | F14: 0 | G14: 0 | H14: 0 | I14: 0 | J14: =SUM(F14:I14) -> 0 | K14: 13
A15: 1.1.11 | B15: Lijado y limpieza de ductos de gas en áreas de cocina | C15: TRAMO 1 | D15: m² | E15: 90 | F15: 0 | G15: 0 | H15: 0 | I15: 0 | J15: =SUM(F15:I15) -> 0 | K15: 12
A16: 1.1.12 | B16: Limpieza de rejillas de contadores | C16: TRAMO 1 | D16: m² | E16: 20 | F16: 0 | G16: 0 | H16: 0 | I16: 0 | J16: =SUM(F16:I16) -> 0 | K16: 14
A17: 1.2.1 | B17: Protección de ventanas con plástico | C17: TRAMO 2 | D17: m² | E17: 900 | F17: 0 | G17: 0 | H17: 0 | I17: 0 | J17: =SUM(F17:I17) -> 0 | K17: 3
... A30: 1.3.3 | B30: Lavado de vidrios, incluyendo la marquesina | C30: TRAMO 3 | D30: m² | E30: 640 | F30: 0 | G30: 0 | H30: 0 | I30: 0 | J30: =SUM(F30:I30) -> 0 | K30: 10
B33: Archivos procesados
A34: N.º | B34: Archivo | C34: Fecha Corte
A35: 1 | B35: Avance_Real_DARCA2_24Ago-29Ago.xlsx | C35: 46263
A36: 2 | B36: Avance_Real_DARCA2_31Ago-05Sep.xlsx | C36: 46270
A37: 3 | B37: Avance_Real_DARCA2_7Sep-12Sep.xlsx | C37: 46277
A38: 4 | B38: Avance_Real_DARCA2_14Sep-19Sep.xlsx | C38: 46284
B41: Validaciones y advertencias
A42: Nivel | B42: Detalle | C42: Archivo | J42: Fila | K42: Ítem
A43: ADVERTENCIA | B43: ACTIVIDAD_VACIA: WBS 1.3.1 sin nombre; se vincula por WBS. | C43: Avance_Real_DARCA2_14Sep-19Sep.xlsx | J43: 27
A44: ADVERTENCIA | B44: ACTIVIDAD_VACIA: WBS 1.3.1 sin nombre; se vincula por WBS. | C44: Avance_Real_DARCA2_31Ago-05Sep.xlsx | J44: 27
A45: ADVERTENCIA | B45: ACTIVIDAD_VACIA: WBS 1.3.1 sin nombre; se vincula por WBS. | C45: Avance_Real_DARCA2_7Sep-12Sep.xlsx | J45: 27
A46: INFO | B46: PRECISION: Cantidades a 6 decimales; precios y cálculos monetarios sin redondeo intermedio, presentación a dos decimales.

Sheet Presupuesto
A2: Presupuesto contractual
A3: Fuente: Edificio Darca II - fachada (2).xlsx / Ppto Ajustado
A5: Ítem | B5: Concepto | C5: Descripción | D5: Unidad | E5: Cantidad contratada | F5: Precio unitario | G5: Valor contractual fuente | H5: Fila de origen
A6: 1 | B6: Limpieza superficie | C6: Limpieza de fachada en ladrillo, incluyendo la eliminación de hollín, marcas color naranja y mugre por polución ambiental, utilizando hidrolavadora de 3000 psi. | D6: m² | E6: 3744 | F6: 2707.0473 | G6: 10135185 | H6: 5
A7: 2 | B7: Reparaciones menores | C7: Reemplazo de piezas rotas o deterioradas, emboquillado de fisuras con mortero impermeabilizado y Sika Latex. | D7: und | E7: 500 | F7: 12761.794 | G7: 6380897.1 | H7: 6
A8: 3 | B8: Protecciones | C8: Protección de ventanas con plástico y limpieza de vidrios y marcos. | D8: m² | E8: 1800 | F8: 4157.2511 | G8: 7483052.1 | H8: 7
A9: 4 | B9: Emboquillado | C9: Suministro y aplicación de mortero impermeabilizante en toda la fachada, incluyendo muros laterales. | D9: m² | E9: 3744 | F9: 4060.5709 | G9: 15202777 | H9: 8
A10: 5 | B10: Lavado | C10: Lavado con rinse o ácido especializado para fachadas, tras el emboquillado. | D10: m² | E10: 3744 | F10: 6090.8563 | G10: 22804166 | H10: 9
A11: 6 | B11: Suministro y aplicación | C11: Aplicación de dos manos de SIKA impermeabilizante 10 años, en toda la fachada, incluyendo muros laterales y ladrillo del cerramiento, con aspersor a 360 psi. | D11: m² | E11: 3744 | F11: 11359.93 | G11: 42531580 | H11: 10
A12: 7 | B12: Resane y reparación | C12: Resane de muros laterales, impermeabilización y pintura color blanca de alta resistencia. | D12: m² | E12: 270 | F12: 18272.569 | G12: 4933593.6 | H12: 11
A13: 8 | B13: Vidrios y marcos | C13: Lavado de vidrios, incluyendo flanches | D13: m² | E13: 1800 | F13: 6284.2169 | G13: 11311590 | H13: 12
A14: 9 | B14: Vidrios y marcos | C14: Pintura de marcos y flanches, aplicación de silicona antihongos y reparación de marcos defectuosos. | D14: ml | E14: 1248 | F14: 10344.788 | G14: 12910295 | H14: 13
A15: 10 | B15: Fachada flotante | C15: Lavado de vidrios, incluyendo la marquesina. | D15: m² | E15: 640 | F15: 6284.2169 | G15: 4021898.8 | H15: 14
A16: 11 | B16: Concreto abuzar | C16: Lavado de concreto en fachada flotante, tanto interno como externo. | D16: m² | E16: 192 | F16: 6960.9787 | G16: 1336507.9 | H16: 15
A17: 12 | B17: Ductos de gas | C17: Lijado y limpieza de ductos de gas en áreas de cocina | D17: m² | E17: 180 | F17: 6477.5774 | G17: 1165963.9 | H17: 16
... A19: 14 | B19: Rejillas | C19: Limpieza de rejillas de contadores | D19: m² | E19: 40 | F19: 9668.0259 | G19: 386721.04 | H19: 18
B23: Administracion | E23: 0.1
B24: Imprevistos | E24: 0.04
B25: Utilidad | E25: 0.05
B26: IVA sobre utilidad | E26: 0.19
B28: Costos directos contractuales | G28: 1.4172572e+08
B29: Total contractual con AIU e IVA | G29: 170000000
